.gitignore
MANIFEST.in
README.rst
bootstrap.py
buildout.cfg
setup.cfg
setup.py
docs/HISTORY.txt
zopeskel/__init__.py
zopeskel.browserlayer.egg-info/PKG-INFO
zopeskel.browserlayer.egg-info/SOURCES.txt
zopeskel.browserlayer.egg-info/dependency_links.txt
zopeskel.browserlayer.egg-info/entry_points.txt
zopeskel.browserlayer.egg-info/namespace_packages.txt
zopeskel.browserlayer.egg-info/not-zip-safe
zopeskel.browserlayer.egg-info/requires.txt
zopeskel.browserlayer.egg-info/top_level.txt
zopeskel/browserlayer/TODO.txt
zopeskel/browserlayer/__init__.py
zopeskel/browserlayer/browserlayer.py
zopeskel/browserlayer/templates/browserlayer/bootstrap.py
zopeskel/browserlayer/templates/browserlayer/buildout.cfg_tmpl
zopeskel/browserlayer/templates/browserlayer/plone.cfg
zopeskel/browserlayer/templates/browserlayer/setup.cfg
zopeskel/browserlayer/templates/browserlayer/setup.py_tmpl
zopeskel/browserlayer/templates/browserlayer/+namespace_package+/+package+/configure.zcml_tmpl
zopeskel/browserlayer/templates/browserlayer/+namespace_package+/+package+/version.txt_tmpl
zopeskel/browserlayer/templates/browserlayer/+namespace_package+/+package+/browser/__init__.py
zopeskel/browserlayer/templates/browserlayer/+namespace_package+/+package+/browser/configure.zcml_tmpl
zopeskel/browserlayer/templates/browserlayer/+namespace_package+/+package+/browser/interfaces.py_tmpl
zopeskel/browserlayer/templates/browserlayer/+namespace_package+/+package+/browser/viewlet.pt_tmpl
zopeskel/browserlayer/templates/browserlayer/+namespace_package+/+package+/browser/viewlets.py_tmpl
zopeskel/browserlayer/templates/browserlayer/+namespace_package+/+package+/browser/resources/README.txt_tmpl
zopeskel/browserlayer/templates/browserlayer/+namespace_package+/+package+/browser/resources/main.css_tmpl
zopeskel/browserlayer/templates/browserlayer/+namespace_package+/+package+/browser/resources/main.js_tmpl
zopeskel/browserlayer/templates/browserlayer/+namespace_package+/+package+/locales/README.txt
zopeskel/browserlayer/templates/browserlayer/+namespace_package+/+package+/profiles/default/browserlayer.xml_tmpl
zopeskel/browserlayer/templates/browserlayer/+namespace_package+/+package+/profiles/default/cssregistry.xml_tmpl
zopeskel/browserlayer/templates/browserlayer/+namespace_package+/+package+/profiles/default/jsregistry.xml_tmpl
