Metadata-Version: 1.0
Name: zopeskel.browserlayer
Version: 1.0
Summary: Paster templates for Zope browserlayer package
Home-page: http://github.com/smcmahon/zopeskel.browserlayer
Author: ZopeSkel Team
Author-email: zopeskel@lists.plone.org
License: GPL 2
Keywords: plone zope browserlayer
Platform: UNKNOWN
Classifier: Programming Language :: Python
Classifier: Framework :: Plone
Classifier: Framework :: Zope3
Classifier: Topic :: Software Development :: Libraries :: Python Modules
